[
  {
    "_fbKey": "620611:6206112605076",
    "Id": 6206112605076,
    "companyId": "620611",
    "BookingStatus": "Pending",
    "BookingSource": "Website",
    "Name": "Safinah Mohammed",
    "PhoneNo": "",
    "PickAddress": "Kew, Invercargill City, Southland, 9812, New Zealand",
    "PickLatLng": "-46.436579,168.355424",
    "DropAddress": "Ascot Park Hotel, Tay Street, Hawthorndale, Invercargill City, Southland, 9810, New Zealand",
    "DropLatLng": "-46.4052075,168.3937589",
    "VehicleType": "",
    "PaymentMethod": "Card",
    "EstimatedFare": 0,
    "BookingDateTime": "2026-05-07T15:17:41.038Z",
    "Notes": "",
    "Passengers": 1,
    "serviceType": "taxi",
    "bookingType": "",
    "paymentStatus": "paid",
    "DriverId": 0,
    "VehicleId": 0,
    "DispatchTimebefore": "0"
  }
]