[
  {
    "Id": 61126051212,
    "BookingStatus": "Active",
    "companyId": "620611",
    "DriverId": "D002",
    "VehicleId": "TAXI02",
    "VehicleNo": "TAXI02",
    "Name": "Street Pickup",
    "PhoneNo": "",
    "PickAddress": "Hail - -46.39627, 168.35142",
    "DropAddress": "",
    "PickLatLng": "-46.3962666,168.3514204",
    "DropLatLng": "",
    "BookingDateTime": "2026-05-12T14:12:39.608Z",
    "JobCompleteTime": "",
    "BookingSource": "Hail",
    "booking_type": "Hail",
    "JobMins": 0,
    "UserFName": "TestDriver",
    "UserLName": "Two",
    "Route": "",
    "bookingidx": 61126051212
  }
]