[
  {
    "id": "REG-1777118438459",
    "status": "deactivated",
    "submittedAt": 1777118438459,
    "company": "Test Taxis",
    "name": "Joe Bloggs",
    "email": "joe@test.co.nz",
    "phone": "",
    "passwordHash": "secret123",
    "businessNumber": "9876543",
    "fleetSize": "8",
    "area": "Dunedin",
    "country": "NZ",
    "companyId": "926535",
    "approvedAt": 1777118449265,
    "trialStart": 1777118449265,
    "trialEnd": 1777982449265,
    "graceEnd": null,
    "rejectedAt": null,
    "rejectedReason": null
  },
  {
    "id": "REG-1777118567416",
    "status": "rejected",
    "submittedAt": 1777118567416,
    "company": "Invercargill Taxis Southland",
    "name": "Safinah Mohammed",
    "email": "haziiscoo12@gmail.com",
    "phone": "safinahmohammed@hotmail.com",
    "passwordHash": "Batman10",
    "businessNumber": "12345",
    "fleetSize": "12",
    "area": "N/A",
    "country": "NZ",
    "companyId": null,
    "approvedAt": null,
    "trialStart": null,
    "trialEnd": null,
    "graceEnd": null,
    "rejectedAt": 1777119433634,
    "rejectedReason": "Does not meet requirements"
  },
  {
    "id": "REG-1777118637820",
    "status": "rejected",
    "submittedAt": 1777118637820,
    "company": "Invercargill Taxis Southland",
    "name": "Safinah Mohammed",
    "email": "haziiscool12@gmail.com",
    "phone": "safinahmohammed@hotmail.com",
    "passwordHash": "Batman10",
    "businessNumber": "12345",
    "fleetSize": "12",
    "area": "N/A",
    "country": "NZ",
    "companyId": null,
    "approvedAt": null,
    "trialStart": null,
    "trialEnd": null,
    "graceEnd": null,
    "rejectedAt": 1777119425478,
    "rejectedReason": "Service area not covered"
  },
  {
    "id": "REG-1777119455429",
    "status": "deactivated",
    "submittedAt": 1777119455429,
    "company": "Firebase Test Co",
    "name": "Alice Test",
    "email": "alicetest.bw2026@gmail.com",
    "phone": "",
    "passwordHash": "Test1234!",
    "businessNumber": "",
    "fleetSize": "",
    "area": "",
    "country": "NZ",
    "companyId": "663539",
    "approvedAt": 1777119456635,
    "trialStart": 1777119456635,
    "trialEnd": 1777983456635,
    "graceEnd": null,
    "rejectedAt": null,
    "rejectedReason": null,
    "ownerUid": "AoiINxMMbfcNAfrxr5NJjnCXKpA3"
  },
  {
    "id": "REG-1777119773110",
    "status": "active",
    "submittedAt": 1777119773110,
    "company": "Invercargill Taxis Southland LTD",
    "name": "Hasnat Abdullah",
    "email": "haziiscool12@gmail.com",
    "phone": "0210497275",
    "passwordHash": "123456",
    "businessNumber": "1234567",
    "fleetSize": "12",
    "area": "Invercargill",
    "country": "NZ",
    "companyId": "417942",
    "approvedAt": 1777119794179,
    "trialStart": 1777119794179,
    "trialEnd": 1777983794179,
    "graceEnd": null,
    "rejectedAt": null,
    "rejectedReason": null,
    "ownerUid": null
  },
  {
    "id": "REG-1777120835204",
    "status": "active",
    "submittedAt": 1777120835204,
    "company": "Invercargill Taxis Southland",
    "name": "Safinah Mohammed",
    "email": "hasnat.abdullahcool@gmail.com",
    "phone": "021304322",
    "passwordHash": "123456",
    "businessNumber": "1234567",
    "fleetSize": "12",
    "area": "Invercargill",
    "country": "NZ",
    "companyId": "714479",
    "approvedAt": 1777120877144,
    "trialStart": 1777120877144,
    "trialEnd": 1777984877144,
    "graceEnd": null,
    "rejectedAt": null,
    "rejectedReason": null,
    "ownerUid": "dBJKSLmLY8RZ8C523xAsCfgZcgA2"
  },
  {
    "id": "REG-1777122293876",
    "status": "rejected",
    "submittedAt": 1777122293876,
    "company": "Test Co Ltd",
    "name": "Bob Test",
    "email": "bobtest.bw2026@gmail.com",
    "phone": "021555999",
    "passwordHash": "testpass123",
    "businessNumber": "BN-99999",
    "fleetSize": "5",
    "area": "Wellington",
    "country": "NZ",
    "companyId": null,
    "ownerUid": "AYcHuhsWTfZCEW5MZkRWa4PY0z03",
    "approvedAt": null,
    "trialStart": null,
    "trialEnd": null,
    "graceEnd": null,
    "rejectedAt": 1777206356916,
    "rejectedReason": "Service area not covered"
  },
  {
    "id": "REG-1777122411766",
    "status": "active",
    "submittedAt": 1777122411766,
    "company": "Invercargill Taxis Southland",
    "name": "Mustafa Tekinkaya",
    "email": "h2hasnat@gmail.com",
    "phone": "",
    "passwordHash": "123456",
    "businessNumber": "1234567",
    "fleetSize": "12",
    "area": "Invercargill",
    "country": "NZ",
    "companyId": "566110",
    "ownerUid": "OclsoUOLixWzN2bCatYUiUO7ijo1",
    "approvedAt": 1777122426051,
    "trialStart": 1777122426051,
    "trialEnd": 1777986426051,
    "graceEnd": null,
    "rejectedAt": null,
    "rejectedReason": null
  },
  {
    "id": "REG-1777122911808",
    "status": "active",
    "submittedAt": 1777122911808,
    "company": "testtttaxis",
    "name": "invercargill taxis ltd",
    "email": "hasnatballz@gmail.com",
    "phone": "",
    "passwordHash": "123456",
    "businessNumber": "123",
    "fleetSize": "123",
    "area": "Invercargill",
    "country": "NZ",
    "companyId": "573862",
    "ownerUid": "K0uQqmc8q0VuKcRJZPV7UfXFi2g1",
    "approvedAt": 1777122938834,
    "trialStart": 1777122938834,
    "trialEnd": 1777986938834,
    "graceEnd": null,
    "rejectedAt": null,
    "rejectedReason": null
  },
  {
    "id": "REG-1777124350088",
    "status": "active",
    "submittedAt": 1777124350088,
    "company": "BlueStar Taxis LTD",
    "name": "Hazi",
    "email": "harvanafootball@gmail.com",
    "phone": "",
    "passwordHash": "123456",
    "businessNumber": "1231231",
    "fleetSize": "12",
    "area": "Invercargill",
    "country": "NZ",
    "companyId": "432886",
    "ownerUid": "ge2vwQtQkkPuvWS0DrrYUh0cZyf1",
    "approvedAt": 1777124398343,
    "trialStart": 1777124398343,
    "trialEnd": 1777988398343,
    "graceEnd": null,
    "rejectedAt": null,
    "rejectedReason": null
  },
  {
    "id": "REG-1777178779258",
    "companyId": "131040",
    "company": "TestTaxis",
    "name": "Test Admin",
    "email": "admin@testtaxis.com",
    "phone": "",
    "country": "NZ",
    "area": "Invercargill",
    "fleetSize": 5,
    "status": "active",
    "approvedAt": 1777190057124,
    "trialStart": null,
    "trialEnd": null,
    "graceEnd": null,
    "ownerUid": "",
    "passwordHash": ""
  },
  {
    "id": "REG-1777205800091",
    "status": "trial",
    "submittedAt": 1777205800091,
    "company": "Invercargill Taxis Southland LTD",
    "name": "Safinah Mohammed",
    "email": "safinhmohammed@hotmail.com",
    "phone": "021304322",
    "passwordHash": "safinah123",
    "businessNumber": "",
    "fleetSize": "10",
    "area": "Invercargill",
    "country": "NZ",
    "companyId": "374161",
    "ownerUid": null,
    "approvedAt": 1777206139243,
    "trialStart": 1777206139243,
    "trialEnd": 1778070139243,
    "graceEnd": null,
    "rejectedAt": null,
    "rejectedReason": null
  }
]